pyregister2/__init__.py
pyregister2/pyregister.py
pyregister2/bin/32/libpyregister.a
pyregister2/bin/32/libpyregister.so
pyregister2/bin/32/pyregister.dll
pyregister2/bin/64/libpyregister.a
pyregister2/bin/64/libpyregister.so
pyregister2/bin/64/pyregister.dll
pyregister2-1.1.5.dist-info/METADATA
pyregister2-1.1.5.dist-info/WHEEL
pyregister2-1.1.5.dist-info/top_level.txt
pyregister2-1.1.5.dist-info/RECORD
